gkey/__init__.py
gkey/myfunctions.py
gKey-0.0.2.dist-info/METADATA
gKey-0.0.2.dist-info/WHEEL
gKey-0.0.2.dist-info/top_level.txt
gKey-0.0.2.dist-info/RECORD
