Metadata-Version: 2.1
Name: gKey
Version: 0.0.2
Summary: Python library used to encrypt and decrypt strings in the simplest possible way, while also being incredibly secure.
Home-page: https://github.com/gdavid7/gkey
Author: gdavid7
License: UNKNOWN
Platform: UNKNOWN
Classifier: Programming Language :: Python :: 3
Classifier: License :: OSI Approved :: MIT License
Classifier: Operating System :: OS Independent
